super_mario/__init__.py
super_mario/base_pipeline.py
super_mario/decorators.py
super_mario/exceptions.py
super_mario/mappers.py
super_mario/binders/__init__.py
super_mario/binders/django/__init__.py
super_mario/binders/django/management.py
super_mario/utils/__init__.py
super_mario/utils/formatters.py
super_mario/utils/lists.py
super_mario/utils/types.py
super_mario-0.0.5.dist-info/LICENSE
super_mario-0.0.5.dist-info/METADATA
super_mario-0.0.5.dist-info/WHEEL
super_mario-0.0.5.dist-info/top_level.txt
super_mario-0.0.5.dist-info/RECORD
