Metadata-Version: 2.1
Name: super-mario
Version: 0.0.5
Summary: Library for separating data input, output and processing in your business application.
Home-page: https://github.com/best-doctor/Mario/
Author: Ilya Lebedev
Author-email: melevir@gmail.com
License: MIT
Keywords: project structure
Platform: UNKNOWN
Classifier: Development Status :: 2 - Pre-Alpha
Classifier: Intended Audience :: Developers
Classifier: License :: Freely Distributable
Classifier: Programming Language :: Python :: 3 :: Only
Classifier: Programming Language :: Python :: 3.7
Classifier: Programming Language :: Python :: 3.8
Classifier: Programming Language :: Python :: 3.9
Classifier: Programming Language :: Python :: 3.10
Classifier: Topic :: Software Development
Classifier: Topic :: Software Development :: Libraries :: Python Modules
License-File: LICENSE
Requires-Dist: setuptools
Requires-Dist: wrapt (>=1.13.3)
Requires-Dist: typing-inspect (>=0.7.1)
